{"legislative_session": "2025-2026", "identifier": "A9088", "title": "Establishes a weekend child day care assistance program for New York army and air national guard members", "from_organization": "~{\"classification\": \"lower\"}", "classification": ["bill"], "subject": [], "abstracts": [{"note": "", "abstract": "Establishes a weekend child day care assistance program to provide for child day care at a child care provider for New York army and air national guard members on drill weekends."}], "other_titles": [], "other_identifiers": [], "actions": [{"description": "REFERRED TO GOVERNMENTAL OPERATIONS", "date": "2025-09-12", "organization_id": "~{\"classification\": \"lower\"}", "classification": ["referral-committee"], "related_entities": [{"name": "GOVERNMENTAL OPERATIONS", "entity_type": "organization", "organization_id": null}]}], "sponsorships": [{"name": "Pamela J. Hunter", "classification": "primary", "entity_type": "person", "primary": true, "person_id": "~{\"name\": \"Pamela J. Hunter\"}", "organization_id": null}], "related_bills": [{"identifier": "S 6424", "legislative_session": "2025-2026", "relation_type": "companion"}, {"identifier": "S 6424", "legislative_session": "2025-2026", "relation_type": "companion"}], "versions": [{"note": "A9088", "links": [{"url": "http://assembly.state.ny.us/leg/?sh=printbill&bn=A9088&term=2025&Text=Y", "media_type": "text/html"}, {"url": "http://legislation.nysenate.gov/pdf/bills/2025/A9088", "media_type": "application/pdf"}], "date": "", "classification": ""}], "documents": [], "citations": [], "sources": [{"url": "https://legislation.nysenate.gov/api/3/bills/2025-2026/A9088?summary=&detail=", "note": ""}, {"url": "http://www.nysenate.gov/legislation/bills/2025/A9088", "note": ""}, {"url": "https://nyassembly.gov/leg/?bn=A09088&term=2025", "note": ""}], "extras": {}, "jurisdiction": {"id": "ocd-jurisdiction/country:us/state:ny/government", "name": "New York", "classification": "state", "division_id": "ocd-division/country:us/state:ny"}, "scraped_at": "2025-12-14T08:16:02+00:00", "_id": "2166a402-d8c5-11f0-abcb-c66867e5dc6b"}