{"legislative_session": "2025-2026", "identifier": "A9004", "title": "Establishes the small business working group to identify the twenty-five provisions of law or rules that are most frequently enforced through issuance of notices of violation and most issued to small businesses", "from_organization": "~{\"classification\": \"lower\"}", "classification": ["bill"], "subject": [], "abstracts": [{"note": "", "abstract": "Establishes the small business working group to identify the twenty-five provisions of law or rules that are most frequently enforced through issuance of notices of violation and most frequently issued to small businesses; requires such working group to evaluate such provisions of law or rules to determine whether changes should be made to such provisions."}], "other_titles": [], "other_identifiers": [], "actions": [{"description": "REFERRED TO SMALL BUSINESS", "date": "2025-08-13", "organization_id": "~{\"classification\": \"lower\"}", "classification": ["referral-committee"], "related_entities": [{"name": "SMALL BUSINESS", "entity_type": "organization", "organization_id": null}]}], "sponsorships": [{"name": "Alex Bores", "classification": "primary", "entity_type": "person", "primary": true, "person_id": "~{\"name\": \"Alex Bores\"}", "organization_id": null}], "related_bills": [], "versions": [{"note": "A9004", "links": [{"url": "http://assembly.state.ny.us/leg/?sh=printbill&bn=A9004&term=2025&Text=Y", "media_type": "text/html"}, {"url": "http://legislation.nysenate.gov/pdf/bills/2025/A9004", "media_type": "application/pdf"}], "date": "", "classification": ""}], "documents": [], "citations": [], "sources": [{"url": "https://legislation.nysenate.gov/api/3/bills/2025-2026/A9004?summary=&detail=", "note": ""}, {"url": "http://www.nysenate.gov/legislation/bills/2025/A9004", "note": ""}, {"url": "https://nyassembly.gov/leg/?bn=A09004&term=2025", "note": ""}], "extras": {}, "jurisdiction": {"id": "ocd-jurisdiction/country:us/state:ny/government", "name": "New York", "classification": "state", "division_id": "ocd-division/country:us/state:ny"}, "scraped_at": "2025-12-17T08:18:41+00:00", "_id": "fefd2bee-db20-11f0-9550-f6a001f5a24b"}